{
  "dataset": "AccidentsBig.csv",
  "generated_at": "2025-12-06T07:39:51.040149Z",
  "basic": {
    "rows": 1048575,
    "cols": [
      "Accident_Index",
      "longitude",
      "latitude",
      "Police_Force",
      "Accident_Severity",
      "Number_of_Vehicles",
      "Number_of_Casualties",
      "Day_of_Week",
      "Time",
      "Local_Authority_(District)",
      "Local_Authority_(Highway)",
      "1st_Road_Class",
      "1st_Road_Number",
      "Road_Type",
      "Speed_limit",
      "Junction_Detail",
      "Junction_Control",
      "2nd_Road_Class",
      "2nd_Road_Number",
      "Pedestrian_Crossing-Human_Control",
      "Pedestrian_Crossing-Physical_Facilities",
      "Light_Conditions",
      "Weather_Conditions",
      "Road_Surface_Conditions",
      "Special_Conditions_at_Site",
      "Carriageway_Hazards",
      "Urban_or_Rural_Area",
      "Did_Police_Officer_Attend_Scene_of_Accident",
      "LSOA_of_Accident_Location",
      "Date"
    ],
    "numeric_cols": [
      "Accident_Index",
      "longitude",
      "latitude",
      "Police_Force",
      "Accident_Severity",
      "Number_of_Vehicles",
      "Number_of_Casualties",
      "Day_of_Week",
      "Local_Authority_(District)",
      "1st_Road_Class",
      "1st_Road_Number",
      "Road_Type",
      "Speed_limit",
      "Junction_Detail",
      "Junction_Control",
      "2nd_Road_Class",
      "2nd_Road_Number",
      "Pedestrian_Crossing-Human_Control",
      "Pedestrian_Crossing-Physical_Facilities",
      "Light_Conditions",
      "Weather_Conditions",
      "Road_Surface_Conditions",
      "Special_Conditions_at_Site",
      "Carriageway_Hazards",
      "Urban_or_Rural_Area",
      "Did_Police_Officer_Attend_Scene_of_Accident"
    ],
    "null_counts": {
      "Accident_Index": 988577,
      "longitude": 988577,
      "latitude": 988577,
      "Police_Force": 988577,
      "Accident_Severity": 988577,
      "Number_of_Vehicles": 988577,
      "Number_of_Casualties": 988577,
      "Day_of_Week": 988577,
      "Time": 988578,
      "Local_Authority_(District)": 988577,
      "Local_Authority_(Highway)": 988577,
      "1st_Road_Class": 988577,
      "1st_Road_Number": 988577,
      "Road_Type": 988577,
      "Speed_limit": 988577,
      "Junction_Detail": 988577,
      "Junction_Control": 988577,
      "2nd_Road_Class": 988577,
      "2nd_Road_Number": 988577,
      "Pedestrian_Crossing-Human_Control": 988577,
      "Pedestrian_Crossing-Physical_Facilities": 988577,
      "Light_Conditions": 988577,
      "Weather_Conditions": 988577,
      "Road_Surface_Conditions": 988577,
      "Special_Conditions_at_Site": 988577,
      "Carriageway_Hazards": 988577,
      "Urban_or_Rural_Area": 988577,
      "Did_Police_Officer_Attend_Scene_of_Accident": 988577,
      "LSOA_of_Accident_Location": 988674,
      "Date": 988577
    },
    "sample": [
      {
        "Accident_Index": 1.0,
        "longitude": 78.61039332,
        "latitude": 14.72402585,
        "Police_Force": 1.0,
        "Accident_Severity": 2.0,
        "Number_of_Vehicles": 1.0,
        "Number_of_Casualties": 1.0,
        "Day_of_Week": 3.0,
        "Time": "17:42",
        "Local_Authority_(District)": 12.0,
        "Local_Authority_(Highway)": "E09000020",
        "1st_Road_Class": 3.0,
        "1st_Road_Number": 3218.0,
        "Road_Type": 6.0,
        "Speed_limit": 30.0,
        "Junction_Detail": 0.0,
        "Junction_Control": -1.0,
        "2nd_Road_Class": -1.0,
        "2nd_Road_Number": 0.0,
        "Pedestrian_Crossing-Human_Control": 0.0,
        "Pedestrian_Crossing-Physical_Facilities": 1.0,
        "Light_Conditions": 1.0,
        "Weather_Conditions": 2.0,
        "Road_Surface_Conditions": 2.0,
        "Special_Conditions_at_Site": 0.0,
        "Carriageway_Hazards": 0.0,
        "Urban_or_Rural_Area": 1.0,
        "Did_Police_Officer_Attend_Scene_of_Accident": 1.0,
        "LSOA_of_Accident_Location": "E01002849",
        "Date": "04-01-2018"
      },
      {
        "Accident_Index": 2.0,
        "longitude": 78.53404158,
        "latitude": 14.76235346,
        "Police_Force": 1.0,
        "Accident_Severity": 3.0,
        "Number_of_Vehicles": 1.0,
        "Number_of_Casualties": 1.0,
        "Day_of_Week": 4.0,
        "Time": "17:36",
        "Local_Authority_(District)": 12.0,
        "Local_Authority_(Highway)": "E09000020",
        "1st_Road_Class": 4.0,
        "1st_Road_Number": 450.0,
        "Road_Type": 3.0,
        "Speed_limit": 30.0,
        "Junction_Detail": 6.0,
        "Junction_Control": 2.0,
        "2nd_Road_Class": 5.0,
        "2nd_Road_Number": 0.0,
        "Pedestrian_Crossing-Human_Control": 0.0,
        "Pedestrian_Crossing-Physical_Facilities": 5.0,
        "Light_Conditions": 4.0,
        "Weather_Conditions": 1.0,
        "Road_Surface_Conditions": 1.0,
        "Special_Conditions_at_Site": 0.0,
        "Carriageway_Hazards": 0.0,
        "Urban_or_Rural_Area": 1.0,
        "Did_Police_Officer_Attend_Scene_of_Accident": 1.0,
        "LSOA_of_Accident_Location": "E01002909",
        "Date": "05-01-2018"
      },
      {
        "Accident_Index": 3.0,
        "longitude": 78.47087739,
        "latitude": 14.74560635,
        "Police_Force": 1.0,
        "Accident_Severity": 3.0,
        "Number_of_Vehicles": 2.0,
        "Number_of_Casualties": 1.0,
        "Day_of_Week": 5.0,
        "Time": "00:15",
        "Local_Authority_(District)": 12.0,
        "Local_Authority_(Highway)": "E09000020",
        "1st_Road_Class": 5.0,
        "1st_Road_Number": 0.0,
        "Road_Type": 6.0,
        "Speed_limit": 30.0,
        "Junction_Detail": 0.0,
        "Junction_Control": -1.0,
        "2nd_Road_Class": -1.0,
        "2nd_Road_Number": 0.0,
        "Pedestrian_Crossing-Human_Control": 0.0,
        "Pedestrian_Crossing-Physical_Facilities": 0.0,
        "Light_Conditions": 4.0,
        "Weather_Conditions": 1.0,
        "Road_Surface_Conditions": 1.0,
        "Special_Conditions_at_Site": 0.0,
        "Carriageway_Hazards": 0.0,
        "Urban_or_Rural_Area": 1.0,
        "Did_Police_Officer_Attend_Scene_of_Accident": 1.0,
        "LSOA_of_Accident_Location": "E01002857",
        "Date": "06-01-2018"
      },
      {
        "Accident_Index": 4.0,
        "longitude": 78.55799399,
        "latitude": 14.66712796,
        "Police_Force": 1.0,
        "Accident_Severity": 3.0,
        "Number_of_Vehicles": 1.0,
        "Number_of_Casualties": 1.0,
        "Day_of_Week": 6.0,
        "Time": "10:35",
        "Local_Authority_(District)": 12.0,
        "Local_Authority_(Highway)": "E09000020",
        "1st_Road_Class": 3.0,
        "1st_Road_Number": 3220.0,
        "Road_Type": 6.0,
        "Speed_limit": 30.0,
        "Junction_Detail": 0.0,
        "Junction_Control": -1.0,
        "2nd_Road_Class": -1.0,
        "2nd_Road_Number": 0.0,
        "Pedestrian_Crossing-Human_Control": 0.0,
        "Pedestrian_Crossing-Physical_Facilities": 0.0,
        "Light_Conditions": 1.0,
        "Weather_Conditions": 1.0,
        "Road_Surface_Conditions": 1.0,
        "Special_Conditions_at_Site": 0.0,
        "Carriageway_Hazards": 0.0,
        "Urban_or_Rural_Area": 1.0,
        "Did_Police_Officer_Attend_Scene_of_Accident": 1.0,
        "LSOA_of_Accident_Location": "E01002840",
        "Date": "07-01-2018"
      },
      {
        "Accident_Index": 5.0,
        "longitude": 78.57643143,
        "latitude": 14.70344275,
        "Police_Force": 1.0,
        "Accident_Severity": 3.0,
        "Number_of_Vehicles": 1.0,
        "Number_of_Casualties": 1.0,
        "Day_of_Week": 2.0,
        "Time": "21:13",
        "Local_Authority_(District)": 12.0,
        "Local_Authority_(Highway)": "E09000020",
        "1st_Road_Class": 6.0,
        "1st_Road_Number": 0.0,
        "Road_Type": 6.0,
        "Speed_limit": 30.0,
        "Junction_Detail": 0.0,
        "Junction_Control": -1.0,
        "2nd_Road_Class": -1.0,
        "2nd_Road_Number": 0.0,
        "Pedestrian_Crossing-Human_Control": 0.0,
        "Pedestrian_Crossing-Physical_Facilities": 0.0,
        "Light_Conditions": 7.0,
        "Weather_Conditions": 1.0,
        "Road_Surface_Conditions": 2.0,
        "Special_Conditions_at_Site": 0.0,
        "Carriageway_Hazards": 0.0,
        "Urban_or_Rural_Area": 1.0,
        "Did_Police_Officer_Attend_Scene_of_Accident": 1.0,
        "LSOA_of_Accident_Location": "E01002863",
        "Date": "10-01-2018"
      }
    ]
  },
  "severity_distribution": [
    {
      "name": "Unknown",
      "value": 988577
    },
    {
      "name": "3.0",
      "value": 51975
    },
    {
      "name": "2.0",
      "value": 7377
    },
    {
      "name": "1.0",
      "value": 646
    }
  ],
  "by_hour": [
    {
      "hour": 0,
      "count": 23769
    }
  ],
  "by_weekday": [
    {
      "weekday": "Monday",
      "count": 3594
    },
    {
      "weekday": "Tuesday",
      "count": 3480
    },
    {
      "weekday": "Wednesday",
      "count": 3424
    },
    {
      "weekday": "Thursday",
      "count": 3254
    },
    {
      "weekday": "Friday",
      "count": 3303
    },
    {
      "weekday": "Saturday",
      "count": 3344
    },
    {
      "weekday": "Sunday",
      "count": 3370
    }
  ],
  "top_factors": {
    "Local_Authority_(Highway)": [
      {
        "value": "Unknown",
        "count": 988577
      },
      {
        "value": "E10000017",
        "count": 4516
      },
      {
        "value": "E08000003",
        "count": 2336
      },
      {
        "value": "E08000012",
        "count": 2021
      },
      {
        "value": "E10000006",
        "count": 1900
      },
      {
        "value": "E09000033",
        "count": 1564
      }
    ]
  },
  "correlation": {
    "Accident_Index": {
      "Accident_Index": 1.0,
      "longitude": -0.6254749159531812,
      "latitude": -0.04390951260230183,
      "Police_Force": 0.5856001382120213,
      "Accident_Severity": -0.025385332376266497,
      "Number_of_Vehicles": 0.04852316659464017,
      "Number_of_Casualties": 0.13494578631610732,
      "Day_of_Week": 0.008358246069226437,
      "Local_Authority_(District)": 0.7221591674857285,
      "1st_Road_Class": 0.07123492478453981,
      "1st_Road_Number": 0.15226118605640168,
      "Road_Type": -0.02898765322594617,
      "Speed_limit": 0.3150325578227954,
      "Junction_Detail": -0.045311450276087066,
      "Junction_Control": -0.0385320407385591,
      "2nd_Road_Class": -0.038601952352376644,
      "2nd_Road_Number": 0.1041423309721969,
      "Pedestrian_Crossing-Human_Control": 0.023727806209543595,
      "Pedestrian_Crossing-Physical_Facilities": -0.11158029158083277,
      "Light_Conditions": -0.0002584727195682561,
      "Weather_Conditions": 0.09843729920935161,
      "Road_Surface_Conditions": 0.15677431046022208,
      "Special_Conditions_at_Site": 0.05011627226622499,
      "Carriageway_Hazards": 0.04396099936496629,
      "Urban_or_Rural_Area": 0.3615334280728416,
      "Did_Police_Officer_Attend_Scene_of_Accident": 0.006026847550643641
    },
    "longitude": {
      "Accident_Index": -0.6254749159531812,
      "longitude": 1.0,
      "latitude": 0.3622827769200684,
      "Police_Force": -0.32669533117925686,
      "Accident_Severity": 0.05259115898188267,
      "Number_of_Vehicles": -0.031174714017883996,
      "Number_of_Casualties": -0.08716808888152384,
      "Day_of_Week": -0.012169492565631969,
      "Local_Authority_(District)": -0.427734421951729,
      "1st_Road_Class": -0.021865747778064694,
      "1st_Road_Number": -0.11323825314896757,
      "Road_Type": 0.02408935169925899,
      "Speed_limit": -0.18376802111360482,
      "Junction_Detail": 0.03578466864172872,
      "Junction_Control": 0.04084132974491247,
      "2nd_Road_Class": 0.03035964939131614,
      "2nd_Road_Number": -0.06647214786638783,
      "Pedestrian_Crossing-Human_Control": -0.014537017301955469,
      "Pedestrian_Crossing-Physical_Facilities": 0.06153979910952724,
      "Light_Conditions": -0.012843337434222031,
      "Weather_Conditions": -0.06229732879899059,
      "Road_Surface_Conditions": -0.10929402814008336,
      "Special_Conditions_at_Site": -0.03305554819950817,
      "Carriageway_Hazards": -0.030454620508090013,
      "Urban_or_Rural_Area": -0.2164051477556587,
      "Did_Police_Officer_Attend_Scene_of_Accident": 0.008027996831800614
    },
    "latitude": {
      "Accident_Index": -0.04390951260230183,
      "longitude": 0.3622827769200684,
      "latitude": 1.0,
      "Police_Force": -0.05150791951641833,
      "Accident_Severity": -0.03890406880350553,
      "Number_of_Vehicles": 0.0075148827004686974,
      "Number_of_Casualties": 0.05051558373969536,
      "Day_of_Week": -0.006722069346801334,
      "Local_Authority_(District)": -0.020848767071228805,
      "1st_Road_Class": 0.0664943981608233,
      "1st_Road_Number": 0.03162053630315682,
      "Road_Type": -0.012846438882891907,
      "Speed_limit": -0.042269611174963195,
      "Junction_Detail": 0.07353556164702174,
      "Junction_Control": 0.04015828468058685,
      "2nd_Road_Class": 0.05017724179098265,
      "2nd_Road_Number": 0.021894008497940057,
      "Pedestrian_Crossing-Human_Control": 0.018680615511250998,
      "Pedestrian_Crossing-Physical_Facilities": 0.006503630078069529,
      "Light_Conditions": -0.007651712208016425,
      "Weather_Conditions": 0.022702305034415355,
      "Road_Surface_Conditions": 0.002854355792108434,
      "Special_Conditions_at_Site": 0.017174509683430775,
      "Carriageway_Hazards": 0.015572596153258176,
      "Urban_or_Rural_Area": -0.0275421536449899,
      "Did_Police_Officer_Attend_Scene_of_Accident": 0.003124182157257851
    },
    "Police_Force": {
      "Accident_Index": 0.5856001382120213,
      "longitude": -0.32669533117925686,
      "latitude": -0.05150791951641833,
      "Police_Force": 1.0,
      "Accident_Severity": -0.012490448848063806,
      "Number_of_Vehicles": 0.0111064502919736,
      "Number_of_Casualties": 0.07363508051820997,
      "Day_of_Week": 0.004706567238378066,
      "Local_Authority_(District)": 0.9742116525357606,
      "1st_Road_Class": 0.04752969176843424,
      "1st_Road_Number": 0.09257686308362789,
      "Road_Type": -0.03327793682763053,
      "Speed_limit": 0.20738107197607025,
      "Junction_Detail": -0.027962692123636508,
      "Junction_Control": -0.029750483252210032,
      "2nd_Road_Class": -0.03299800570479316,
      "2nd_Road_Number": 0.07820351002907884,
      "Pedestrian_Crossing-Human_Control": 0.015479658302222745,
      "Pedestrian_Crossing-Physical_Facilities": -0.019620116853921777,
      "Light_Conditions": -0.00657124581819453,
      "Weather_Conditions": 0.06255855441975303,
      "Road_Surface_Conditions": 0.09433658556733589,
      "Special_Conditions_at_Site": 0.036214866276364714,
      "Carriageway_Hazards": 0.03351030957778028,
      "Urban_or_Rural_Area": 0.2437592786177385,
      "Did_Police_Officer_Attend_Scene_of_Accident": -0.008089852549822378
    },
    "Accident_Severity": {
      "Accident_Index": -0.025385332376266497,
      "longitude": 0.05259115898188267,
      "latitude": -0.03890406880350553,
      "Police_Force": -0.012490448848063806,
      "Accident_Severity": 1.0,
      "Number_of_Vehicles": 0.10449927729796166,
      "Number_of_Casualties": -0.08268266378998723,
      "Day_of_Week": -0.0057655166819549995,
      "Local_Authority_(District)": -0.016524456839796073,
      "1st_Road_Class": 0.0055468301985319626,
      "1st_Road_Number": -0.00669041138600735,
      "Road_Type": -0.02617783497182019,
      "Speed_limit": -0.0734287346876074,
      "Junction_Detail": 0.05570897089872908,
      "Junction_Control": 0.0707279893131377,
      "2nd_Road_Class": 0.06419614307713845,
      "2nd_Road_Number": 0.024603890313915865,
      "Pedestrian_Crossing-Human_Control": 0.007938686519096719,
      "Pedestrian_Crossing-Physical_Facilities": -0.007568733575720509,
      "Light_Conditions": -0.0678611557921266,
      "Weather_Conditions": 0.010612113011409581,
      "Road_Surface_Conditions": -0.0027745423532889563,
      "Special_Conditions_at_Site": 0.0054033407087635665,
      "Carriageway_Hazards": -0.0030517701291511057,
      "Urban_or_Rural_Area": -0.07289034380983837,
      "Did_Police_Officer_Attend_Scene_of_Accident": 0.11605307963163795
    },
    "Number_of_Vehicles": {
      "Accident_Index": 0.04852316659464017,
      "longitude": -0.031174714017883996,
      "latitude": 0.0075148827004686974,
      "Police_Force": 0.0111064502919736,
      "Accident_Severity": 0.10449927729796166,
      "Number_of_Vehicles": 1.0,
      "Number_of_Casualties": 0.22813106504183905,
      "Day_of_Week": -0.015543989894431539,
      "Local_Authority_(District)": 0.02487797157036779,
      "1st_Road_Class": -0.10804306826860292,
      "1st_Road_Number": 0.0027128028632395365,
      "Road_Type": -0.08257994711154702,
      "Speed_limit": 0.11059591535886136,
      "Junction_Detail": 0.04216919073110514,
      "Junction_Control": 0.04655046466415009,
      "2nd_Road_Class": 0.04403742754364685,
      "2nd_Road_Number": 0.01316059301557465,
      "Pedestrian_Crossing-Human_Control": -0.01799312822071099,
      "Pedestrian_Crossing-Physical_Facilities": -0.05725104867932333,
      "Light_Conditions": -0.045215039672887716,
      "Weather_Conditions": 0.001681762103322384,
      "Road_Surface_Conditions": 0.013140648075391299,
      "Special_Conditions_at_Site": -0.0012199350762367616,
      "Carriageway_Hazards": -0.02697838942498375,
      "Urban_or_Rural_Area": 0.06588615700917508,
      "Did_Police_Officer_Attend_Scene_of_Accident": 0.004334468207597522
    },
    "Number_of_Casualties": {
      "Accident_Index": 0.13494578631610732,
      "longitude": -0.08716808888152384,
      "latitude": 0.05051558373969536,
      "Police_Force": 0.07363508051820997,
      "Accident_Severity": -0.08268266378998723,
      "Number_of_Vehicles": 0.22813106504183905,
      "Number_of_Casualties": 1.0,
      "Day_of_Week": 0.0048244703849712215,
      "Local_Authority_(District)": 0.09978939312738737,
      "1st_Road_Class": -0.05673241042265562,
      "1st_Road_Number": 0.04030150566489288,
      "Road_Type": -0.029874999374578572,
      "Speed_limit": 0.1466097312399669,
      "Junction_Detail": 0.0027044344043560243,
      "Junction_Control": -0.028690938883896788,
      "2nd_Road_Class": -0.018420362229499207,
      "2nd_Road_Number": 0.033683509798964076,
      "Pedestrian_Crossing-Human_Control": 0.002132622802296734,
      "Pedestrian_Crossing-Physical_Facilities": -0.010250390803427009,
      "Light_Conditions": 0.03807114541733603,
      "Weather_Conditions": 0.01174872883653678,
      "Road_Surface_Conditions": 0.05607897389164437,
      "Special_Conditions_at_Site": 0.03009199144146058,
      "Carriageway_Hazards": 0.005840231779932707,
      "Urban_or_Rural_Area": 0.1335871525022806,
      "Did_Police_Officer_Attend_Scene_of_Accident": -0.0889591120506292
    },
    "Day_of_Week": {
      "Accident_Index": 0.008358246069226437,
      "longitude": -0.012169492565631969,
      "latitude": -0.006722069346801334,
      "Police_Force": 0.004706567238378066,
      "Accident_Severity": -0.0057655166819549995,
      "Number_of_Vehicles": -0.015543989894431539,
      "Number_of_Casualties": 0.0048244703849712215,
      "Day_of_Week": 1.0,
      "Local_Authority_(District)": 0.004937149916925668,
      "1st_Road_Class": 0.004350021108909649,
      "1st_Road_Number": 0.007819083389569981,
      "Road_Type": 0.009429584444562848,
      "Speed_limit": -0.010990116720642974,
      "Junction_Detail": 0.0063340358620890755,
      "Junction_Control": 0.0033068374064892663,
      "2nd_Road_Class": 0.005052615708992284,
      "2nd_Road_Number": 0.004827835851308403,
      "Pedestrian_Crossing-Human_Control": 0.0013317688157301886,
      "Pedestrian_Crossing-Physical_Facilities": 0.0030927154138392114,
      "Light_Conditions": 0.014442802089367249,
      "Weather_Conditions": 0.012710985965679237,
      "Road_Surface_Conditions": 0.018156032338970375,
      "Special_Conditions_at_Site": -0.006350423304762056,
      "Carriageway_Hazards": 0.0030016286109226654,
      "Urban_or_Rural_Area": -0.00889730166957208,
      "Did_Police_Officer_Attend_Scene_of_Accident": -0.006304109438709757
    },
    "Local_Authority_(District)": {
      "Accident_Index": 0.7221591674857285,
      "longitude": -0.427734421951729,
      "latitude": -0.020848767071228805,
      "Police_Force": 0.9742116525357606,
      "Accident_Severity": -0.016524456839796073,
      "Number_of_Vehicles": 0.02487797157036779,
      "Number_of_Casualties": 0.09978939312738737,
      "Day_of_Week": 0.004937149916925668,
      "Local_Authority_(District)": 1.0,
      "1st_Road_Class": 0.06358755761950655,
      "1st_Road_Number": 0.12022404865501637,
      "Road_Type": -0.03832747514605079,
      "Speed_limit": 0.2514971397957883,
      "Junction_Detail": -0.03063270590773953,
      "Junction_Control": -0.03492271700445528,
      "2nd_Road_Class": -0.03555457532023262,
      "2nd_Road_Number": 0.08717891589957118,
      "Pedestrian_Crossing-Human_Control": 0.02067071817896562,
      "Pedestrian_Crossing-Physical_Facilities": -0.05106672252249264,
      "Light_Conditions": -0.006674022273571455,
      "Weather_Conditions": 0.07952033939916987,
      "Road_Surface_Conditions": 0.11622614517311984,
      "Special_Conditions_at_Site": 0.04423215943755628,
      "Carriageway_Hazards": 0.0407857118380476,
      "Urban_or_Rural_Area": 0.29750664209271305,
      "Did_Police_Officer_Attend_Scene_of_Accident": -0.005050849362155015
    },
    "1st_Road_Class": {
      "Accident_Index": 0.07123492478453981,
      "longitude": -0.021865747778064694,
      "latitude": 0.0664943981608233,
      "Police_Force": 0.04752969176843424,
      "Accident_Severity": 0.0055468301985319626,
      "Number_of_Vehicles": -0.10804306826860292,
      "Number_of_Casualties": -0.05673241042265562,
      "Day_of_Week": 0.004350021108909649,
      "Local_Authority_(District)": 0.06358755761950655,
      "1st_Road_Class": 1.0,
      "1st_Road_Number": -0.16237450749632795,
      "Road_Type": 0.26114891595001777,
      "Speed_limit": -0.31116741809928183,
      "Junction_Detail": 0.049872163296778224,
      "Junction_Control": 0.09619370609394529,
      "2nd_Road_Class": 0.10383931224325113,
      "2nd_Road_Number": -0.05105503044309023,
      "Pedestrian_Crossing-Human_Control": 0.00019234768893810363,
      "Pedestrian_Crossing-Physical_Facilities": -0.153000297664735,
      "Light_Conditions": -0.03454688127568687,
      "Weather_Conditions": 0.007597445767175625,
      "Road_Surface_Conditions": -0.0018538004451187154,
      "Special_Conditions_at_Site": -0.011624329087063671,
      "Carriageway_Hazards": -0.0023314690733366654,
      "Urban_or_Rural_Area": -0.1609436868906676,
      "Did_Police_Officer_Attend_Scene_of_Accident": 0.04630093296829648
    },
    "1st_Road_Number": {
      "Accident_Index": 0.15226118605640168,
      "longitude": -0.11323825314896757,
      "latitude": 0.03162053630315682,
      "Police_Force": 0.09257686308362789,
      "Accident_Severity": -0.00669041138600735,
      "Number_of_Vehicles": 0.0027128028632395365,
      "Number_of_Casualties": 0.04030150566489288,
      "Day_of_Week": 0.007819083389569981,
      "Local_Authority_(District)": 0.12022404865501637,
      "1st_Road_Class": -0.16237450749632795,
      "1st_Road_Number": 1.0,
      "Road_Type": 0.026876912153716043,
      "Speed_limit": -0.02057841268824755,
      "Junction_Detail": 0.035089560670335265,
      "Junction_Control": 0.014191439570136504,
      "2nd_Road_Class": 0.030225886369775492,
      "2nd_Road_Number": 0.13007762968764738,
      "Pedestrian_Crossing-Human_Control": 0.012292074072436163,
      "Pedestrian_Crossing-Physical_Facilities": 0.029002593973501526,
      "Light_Conditions": 0.0060433152356347865,
      "Weather_Conditions": 0.016364012315091818,
      "Road_Surface_Conditions": 0.03848372064729448,
      "Special_Conditions_at_Site": 0.01831987114229772,
      "Carriageway_Hazards": 0.0034860436690940873,
      "Urban_or_Rural_Area": 0.04289199966697117,
      "Did_Police_Officer_Attend_Scene_of_Accident": 0.003235406088237152
    },
    "Road_Type": {
      "Accident_Index": -0.02898765322594617,
      "longitude": 0.02408935169925899,
      "latitude": -0.012846438882891907,
      "Police_Force": -0.03327793682763053,
      "Accident_Severity": -0.02617783497182019,
      "Number_of_Vehicles": -0.08257994711154702,
      "Number_of_Casualties": -0.029874999374578572,
      "Day_of_Week": 0.009429584444562848,
      "Local_Authority_(District)": -0.03832747514605079,
      "1st_Road_Class": 0.26114891595001777,
      "1st_Road_Number": 0.026876912153716043,
      "Road_Type": 1.0,
      "Speed_limit": -0.24855437633411678,
      "Junction_Detail": 0.12134042873195672,
      "Junction_Control": -0.009801224636823634,
      "2nd_Road_Class": 0.05187386850688243,
      "2nd_Road_Number": -0.08736709995049179,
      "Pedestrian_Crossing-Human_Control": -7.838359808165505e-05,
      "Pedestrian_Crossing-Physical_Facilities": -0.04175625768604896,
      "Light_Conditions": -0.004820905909901197,
      "Weather_Conditions": 0.01012592596716072,
      "Road_Surface_Conditions": -0.007567873120663123,
      "Special_Conditions_at_Site": -0.01525375092900198,
      "Carriageway_Hazards": 0.002675641384790719,
      "Urban_or_Rural_Area": -0.0987322672634486,
      "Did_Police_Officer_Attend_Scene_of_Accident": 0.012504587087321007
    },
    "Speed_limit": {
      "Accident_Index": 0.3150325578227954,
      "longitude": -0.18376802111360482,
      "latitude": -0.042269611174963195,
      "Police_Force": 0.20738107197607025,
      "Accident_Severity": -0.0734287346876074,
      "Number_of_Vehicles": 0.11059591535886136,
      "Number_of_Casualties": 0.1466097312399669,
      "Day_of_Week": -0.010990116720642974,
      "Local_Authority_(District)": 0.2514971397957883,
      "1st_Road_Class": -0.31116741809928183,
      "1st_Road_Number": -0.02057841268824755,
      "Road_Type": -0.24855437633411678,
      "Speed_limit": 1.0,
      "Junction_Detail": -0.2156514947629862,
      "Junction_Control": -0.24648920898223353,
      "2nd_Road_Class": -0.28898304169773986,
      "2nd_Road_Number": -0.015113491131477634,
      "Pedestrian_Crossing-Human_Control": -0.02462550886353125,
      "Pedestrian_Crossing-Physical_Facilities": -0.14271054421648152,
      "Light_Conditions": 0.05628893736774123,
      "Weather_Conditions": 0.05138575383930931,
      "Road_Surface_Conditions": 0.12564212671725447,
      "Special_Conditions_at_Site": 0.06458382661370199,
      "Carriageway_Hazards": 0.06742183936639545,
      "Urban_or_Rural_Area": 0.6903115614698586,
      "Did_Police_Officer_Attend_Scene_of_Accident": -0.1264451366211499
    },
    "Junction_Detail": {
      "Accident_Index": -0.045311450276087066,
      "longitude": 0.03578466864172872,
      "latitude": 0.07353556164702174,
      "Police_Force": -0.027962692123636508,
      "Accident_Severity": 0.05570897089872908,
      "Number_of_Vehicles": 0.04216919073110514,
      "Number_of_Casualties": 0.0027044344043560243,
      "Day_of_Week": 0.0063340358620890755,
      "Local_Authority_(District)": -0.03063270590773953,
      "1st_Road_Class": 0.049872163296778224,
      "1st_Road_Number": 0.035089560670335265,
      "Road_Type": 0.12134042873195672,
      "Speed_limit": -0.2156514947629862,
      "Junction_Detail": 1.0,
      "Junction_Control": 0.6480781223662255,
      "2nd_Road_Class": 0.6900267863713849,
      "2nd_Road_Number": 0.15107576292311803,
      "Pedestrian_Crossing-Human_Control": 0.014655426618854243,
      "Pedestrian_Crossing-Physical_Facilities": 0.21008340304104023,
      "Light_Conditions": -0.017519156311482507,
      "Weather_Conditions": 0.009704900663941673,
      "Road_Surface_Conditions": -0.027079285054881976,
      "Special_Conditions_at_Site": -0.01967718377693226,
      "Carriageway_Hazards": -0.037921158765293624,
      "Urban_or_Rural_Area": -0.1995337249337957,
      "Did_Police_Officer_Attend_Scene_of_Accident": 0.04777023313147147
    },
    "Junction_Control": {
      "Accident_Index": -0.0385320407385591,
      "longitude": 0.04084132974491247,
      "latitude": 0.04015828468058685,
      "Police_Force": -0.029750483252210032,
      "Accident_Severity": 0.0707279893131377,
      "Number_of_Vehicles": 0.04655046466415009,
      "Number_of_Casualties": -0.028690938883896788,
      "Day_of_Week": 0.0033068374064892663,
      "Local_Authority_(District)": -0.03492271700445528,
      "1st_Road_Class": 0.09619370609394529,
      "1st_Road_Number": 0.014191439570136504,
      "Road_Type": -0.009801224636823634,
      "Speed_limit": -0.24648920898223353,
      "Junction_Detail": 0.6480781223662255,
      "Junction_Control": 1.0,
      "2nd_Road_Class": 0.9167761513349084,
      "2nd_Road_Number": 0.135014486805782,
      "Pedestrian_Crossing-Human_Control": 0.007010139299245572,
      "Pedestrian_Crossing-Physical_Facilities": 0.031216470048736965,
      "Light_Conditions": -0.043633765839626935,
      "Weather_Conditions": -0.013110833605121544,
      "Road_Surface_Conditions": -0.035255296695888415,
      "Special_Conditions_at_Site": -0.032808990712985917,
      "Carriageway_Hazards": -0.053953361007790884,
      "Urban_or_Rural_Area": -0.1893872730559809,
      "Did_Police_Officer_Attend_Scene_of_Accident": 0.05067693686741452
    },
    "2nd_Road_Class": {
      "Accident_Index": -0.038601952352376644,
      "longitude": 0.03035964939131614,
      "latitude": 0.05017724179098265,
      "Police_Force": -0.03299800570479316,
      "Accident_Severity": 0.06419614307713845,
      "Number_of_Vehicles": 0.04403742754364685,
      "Number_of_Casualties": -0.018420362229499207,
      "Day_of_Week": 0.005052615708992284,
      "Local_Authority_(District)": -0.03555457532023262,
      "1st_Road_Class": 0.10383931224325113,
      "1st_Road_Number": 0.030225886369775492,
      "Road_Type": 0.05187386850688243,
      "Speed_limit": -0.28898304169773986,
      "Junction_Detail": 0.6900267863713849,
      "Junction_Control": 0.9167761513349084,
      "2nd_Road_Class": 1.0,
      "2nd_Road_Number": 0.06335899429030002,
      "Pedestrian_Crossing-Human_Control": 0.01356739248622907,
      "Pedestrian_Crossing-Physical_Facilities": 0.11208680295592571,
      "Light_Conditions": -0.03564934967704881,
      "Weather_Conditions": -0.009628903343610573,
      "Road_Surface_Conditions": -0.0318610700012185,
      "Special_Conditions_at_Site": -0.03214238786837213,
      "Carriageway_Hazards": -0.05196153457951812,
      "Urban_or_Rural_Area": -0.23737723768799723,
      "Did_Police_Officer_Attend_Scene_of_Accident": 0.038737916662756174
    },
    "2nd_Road_Number": {
      "Accident_Index": 0.1041423309721969,
      "longitude": -0.06647214786638783,
      "latitude": 0.021894008497940057,
      "Police_Force": 0.07820351002907884,
      "Accident_Severity": 0.024603890313915865,
      "Number_of_Vehicles": 0.01316059301557465,
      "Number_of_Casualties": 0.033683509798964076,
      "Day_of_Week": 0.004827835851308403,
      "Local_Authority_(District)": 0.08717891589957118,
      "1st_Road_Class": -0.05105503044309023,
      "1st_Road_Number": 0.13007762968764738,
      "Road_Type": -0.08736709995049179,
      "Speed_limit": -0.015113491131477634,
      "Junction_Detail": 0.15107576292311803,
      "Junction_Control": 0.135014486805782,
      "2nd_Road_Class": 0.06335899429030002,
      "2nd_Road_Number": 1.0,
      "Pedestrian_Crossing-Human_Control": 0.011567664031617526,
      "Pedestrian_Crossing-Physical_Facilities": 0.10465858046561315,
      "Light_Conditions": -0.002522923469775645,
      "Weather_Conditions": 0.007064962682076394,
      "Road_Surface_Conditions": 0.0016172063070375654,
      "Special_Conditions_at_Site": -0.0006585489379937216,
      "Carriageway_Hazards": -0.014429847939663504,
      "Urban_or_Rural_Area": 0.008815749069833553,
      "Did_Police_Officer_Attend_Scene_of_Accident": 0.035585069064491985
    },
    "Pedestrian_Crossing-Human_Control": {
      "Accident_Index": 0.023727806209543595,
      "longitude": -0.014537017301955469,
      "latitude": 0.018680615511250998,
      "Police_Force": 0.015479658302222745,
      "Accident_Severity": 0.007938686519096719,
      "Number_of_Vehicles": -0.01799312822071099,
      "Number_of_Casualties": 0.002132622802296734,
      "Day_of_Week": 0.0013317688157301886,
      "Local_Authority_(District)": 0.02067071817896562,
      "1st_Road_Class": 0.00019234768893810363,
      "1st_Road_Number": 0.012292074072436163,
      "Road_Type": -7.838359808165505e-05,
      "Speed_limit": -0.02462550886353125,
      "Junction_Detail": 0.014655426618854243,
      "Junction_Control": 0.007010139299245572,
      "2nd_Road_Class": 0.01356739248622907,
      "2nd_Road_Number": 0.011567664031617526,
      "Pedestrian_Crossing-Human_Control": 1.0,
      "Pedestrian_Crossing-Physical_Facilities": 0.05180726689688915,
      "Light_Conditions": -0.01628027033784504,
      "Weather_Conditions": -0.00019486955423728914,
      "Road_Surface_Conditions": -0.004708312567556556,
      "Special_Conditions_at_Site": 0.004513921401199066,
      "Carriageway_Hazards": -0.00027719372507588124,
      "Urban_or_Rural_Area": -0.014923391498879012,
      "Did_Police_Officer_Attend_Scene_of_Accident": 0.011212859909190057
    },
    "Pedestrian_Crossing-Physical_Facilities": {
      "Accident_Index": -0.11158029158083277,
      "longitude": 0.06153979910952724,
      "latitude": 0.006503630078069529,
      "Police_Force": -0.019620116853921777,
      "Accident_Severity": -0.007568733575720509,
      "Number_of_Vehicles": -0.05725104867932333,
      "Number_of_Casualties": -0.010250390803427009,
      "Day_of_Week": 0.0030927154138392114,
      "Local_Authority_(District)": -0.05106672252249264,
      "1st_Road_Class": -0.153000297664735,
      "1st_Road_Number": 0.029002593973501526,
      "Road_Type": -0.04175625768604896,
      "Speed_limit": -0.14271054421648152,
      "Junction_Detail": 0.21008340304104023,
      "Junction_Control": 0.031216470048736965,
      "2nd_Road_Class": 0.11208680295592571,
      "2nd_Road_Number": 0.10465858046561315,
      "Pedestrian_Crossing-Human_Control": 0.05180726689688915,
      "Pedestrian_Crossing-Physical_Facilities": 1.0,
      "Light_Conditions": 0.013880059316151059,
      "Weather_Conditions": -0.017391331571377185,
      "Road_Surface_Conditions": -0.03366354428456771,
      "Special_Conditions_at_Site": -0.009812839564399238,
      "Carriageway_Hazards": -0.016809194580011785,
      "Urban_or_Rural_Area": -0.1625294725216146,
      "Did_Police_Officer_Attend_Scene_of_Accident": -0.018420302712894104
    },
    "Light_Conditions": {
      "Accident_Index": -0.0002584727195682561,
      "longitude": -0.012843337434222031,
      "latitude": -0.007651712208016425,
      "Police_Force": -0.00657124581819453,
      "Accident_Severity": -0.0678611557921266,
      "Number_of_Vehicles": -0.045215039672887716,
      "Number_of_Casualties": 0.03807114541733603,
      "Day_of_Week": 0.014442802089367249,
      "Local_Authority_(District)": -0.006674022273571455,
      "1st_Road_Class": -0.03454688127568687,
      "1st_Road_Number": 0.0060433152356347865,
      "Road_Type": -0.004820905909901197,
      "Speed_limit": 0.05628893736774123,
      "Junction_Detail": -0.017519156311482507,
      "Junction_Control": -0.043633765839626935,
      "2nd_Road_Class": -0.03564934967704881,
      "2nd_Road_Number": -0.002522923469775645,
      "Pedestrian_Crossing-Human_Control": -0.01628027033784504,
      "Pedestrian_Crossing-Physical_Facilities": 0.013880059316151059,
      "Light_Conditions": 1.0,
      "Weather_Conditions": 0.1126577939615356,
      "Road_Surface_Conditions": 0.17664142686821813,
      "Special_Conditions_at_Site": -0.0025071742817291878,
      "Carriageway_Hazards": 0.030928414472766397,
      "Urban_or_Rural_Area": 0.0421188160437248,
      "Did_Police_Officer_Attend_Scene_of_Accident": -0.054452112801539145
    },
    "Weather_Conditions": {
      "Accident_Index": 0.09843729920935161,
      "longitude": -0.06229732879899059,
      "latitude": 0.022702305034415355,
      "Police_Force": 0.06255855441975303,
      "Accident_Severity": 0.010612113011409581,
      "Number_of_Vehicles": 0.001681762103322384,
      "Number_of_Casualties": 0.01174872883653678,
      "Day_of_Week": 0.012710985965679237,
      "Local_Authority_(District)": 0.07952033939916987,
      "1st_Road_Class": 0.007597445767175625,
      "1st_Road_Number": 0.016364012315091818,
      "Road_Type": 0.01012592596716072,
      "Speed_limit": 0.05138575383930931,
      "Junction_Detail": 0.009704900663941673,
      "Junction_Control": -0.013110833605121544,
      "2nd_Road_Class": -0.009628903343610573,
      "2nd_Road_Number": 0.007064962682076394,
      "Pedestrian_Crossing-Human_Control": -0.00019486955423728914,
      "Pedestrian_Crossing-Physical_Facilities": -0.017391331571377185,
      "Light_Conditions": 0.1126577939615356,
      "Weather_Conditions": 1.0,
      "Road_Surface_Conditions": 0.33332893430410704,
      "Special_Conditions_at_Site": 0.024189391006490393,
      "Carriageway_Hazards": 0.01949696609189792,
      "Urban_or_Rural_Area": 0.061298757734275344,
      "Did_Police_Officer_Attend_Scene_of_Accident": 0.017790798658151922
    },
    "Road_Surface_Conditions": {
      "Accident_Index": 0.15677431046022208,
      "longitude": -0.10929402814008336,
      "latitude": 0.002854355792108434,
      "Police_Force": 0.09433658556733589,
      "Accident_Severity": -0.0027745423532889563,
      "Number_of_Vehicles": 0.013140648075391299,
      "Number_of_Casualties": 0.05607897389164437,
      "Day_of_Week": 0.018156032338970375,
      "Local_Authority_(District)": 0.11622614517311984,
      "1st_Road_Class": -0.0018538004451187154,
      "1st_Road_Number": 0.03848372064729448,
      "Road_Type": -0.007567873120663123,
      "Speed_limit": 0.12564212671725447,
      "Junction_Detail": -0.027079285054881976,
      "Junction_Control": -0.035255296695888415,
      "2nd_Road_Class": -0.0318610700012185,
      "2nd_Road_Number": 0.0016172063070375654,
      "Pedestrian_Crossing-Human_Control": -0.004708312567556556,
      "Pedestrian_Crossing-Physical_Facilities": -0.03366354428456771,
      "Light_Conditions": 0.17664142686821813,
      "Weather_Conditions": 0.33332893430410704,
      "Road_Surface_Conditions": 1.0,
      "Special_Conditions_at_Site": 0.029706524834531154,
      "Carriageway_Hazards": 0.02568192102127561,
      "Urban_or_Rural_Area": 0.13218730569745976,
      "Did_Police_Officer_Attend_Scene_of_Accident": -0.08314568284907624
    },
    "Special_Conditions_at_Site": {
      "Accident_Index": 0.05011627226622499,
      "longitude": -0.03305554819950817,
      "latitude": 0.017174509683430775,
      "Police_Force": 0.036214866276364714,
      "Accident_Severity": 0.0054033407087635665,
      "Number_of_Vehicles": -0.0012199350762367616,
      "Number_of_Casualties": 0.03009199144146058,
      "Day_of_Week": -0.006350423304762056,
      "Local_Authority_(District)": 0.04423215943755628,
      "1st_Road_Class": -0.011624329087063671,
      "1st_Road_Number": 0.01831987114229772,
      "Road_Type": -0.01525375092900198,
      "Speed_limit": 0.06458382661370199,
      "Junction_Detail": -0.01967718377693226,
      "Junction_Control": -0.032808990712985917,
      "2nd_Road_Class": -0.03214238786837213,
      "2nd_Road_Number": -0.0006585489379937216,
      "Pedestrian_Crossing-Human_Control": 0.004513921401199066,
      "Pedestrian_Crossing-Physical_Facilities": -0.009812839564399238,
      "Light_Conditions": -0.0025071742817291878,
      "Weather_Conditions": 0.024189391006490393,
      "Road_Surface_Conditions": 0.029706524834531154,
      "Special_Conditions_at_Site": 1.0,
      "Carriageway_Hazards": 0.03738077144802069,
      "Urban_or_Rural_Area": 0.07392705666815787,
      "Did_Police_Officer_Attend_Scene_of_Accident": -0.02212675733095642
    },
    "Carriageway_Hazards": {
      "Accident_Index": 0.04396099936496629,
      "longitude": -0.030454620508090013,
      "latitude": 0.015572596153258176,
      "Police_Force": 0.03351030957778028,
      "Accident_Severity": -0.0030517701291511057,
      "Number_of_Vehicles": -0.02697838942498375,
      "Number_of_Casualties": 0.005840231779932707,
      "Day_of_Week": 0.0030016286109226654,
      "Local_Authority_(District)": 0.0407857118380476,
      "1st_Road_Class": -0.0023314690733366654,
      "1st_Road_Number": 0.0034860436690940873,
      "Road_Type": 0.002675641384790719,
      "Speed_limit": 0.06742183936639545,
      "Junction_Detail": -0.037921158765293624,
      "Junction_Control": -0.053953361007790884,
      "2nd_Road_Class": -0.05196153457951812,
      "2nd_Road_Number": -0.014429847939663504,
      "Pedestrian_Crossing-Human_Control": -0.00027719372507588124,
      "Pedestrian_Crossing-Physical_Facilities": -0.016809194580011785,
      "Light_Conditions": 0.030928414472766397,
      "Weather_Conditions": 0.01949696609189792,
      "Road_Surface_Conditions": 0.02568192102127561,
      "Special_Conditions_at_Site": 0.03738077144802069,
      "Carriageway_Hazards": 1.0,
      "Urban_or_Rural_Area": 0.07266414674596126,
      "Did_Police_Officer_Attend_Scene_of_Accident": -0.01080873874450113
    },
    "Urban_or_Rural_Area": {
      "Accident_Index": 0.3615334280728416,
      "longitude": -0.2164051477556587,
      "latitude": -0.0275421536449899,
      "Police_Force": 0.2437592786177385,
      "Accident_Severity": -0.07289034380983837,
      "Number_of_Vehicles": 0.06588615700917508,
      "Number_of_Casualties": 0.1335871525022806,
      "Day_of_Week": -0.00889730166957208,
      "Local_Authority_(District)": 0.29750664209271305,
      "1st_Road_Class": -0.1609436868906676,
      "1st_Road_Number": 0.04289199966697117,
      "Road_Type": -0.0987322672634486,
      "Speed_limit": 0.6903115614698586,
      "Junction_Detail": -0.1995337249337957,
      "Junction_Control": -0.1893872730559809,
      "2nd_Road_Class": -0.23737723768799723,
      "2nd_Road_Number": 0.008815749069833553,
      "Pedestrian_Crossing-Human_Control": -0.014923391498879012,
      "Pedestrian_Crossing-Physical_Facilities": -0.1625294725216146,
      "Light_Conditions": 0.0421188160437248,
      "Weather_Conditions": 0.061298757734275344,
      "Road_Surface_Conditions": 0.13218730569745976,
      "Special_Conditions_at_Site": 0.07392705666815787,
      "Carriageway_Hazards": 0.07266414674596126,
      "Urban_or_Rural_Area": 1.0,
      "Did_Police_Officer_Attend_Scene_of_Accident": -0.10267241327127857
    },
    "Did_Police_Officer_Attend_Scene_of_Accident": {
      "Accident_Index": 0.006026847550643641,
      "longitude": 0.008027996831800614,
      "latitude": 0.003124182157257851,
      "Police_Force": -0.008089852549822378,
      "Accident_Severity": 0.11605307963163795,
      "Number_of_Vehicles": 0.004334468207597522,
      "Number_of_Casualties": -0.0889591120506292,
      "Day_of_Week": -0.006304109438709757,
      "Local_Authority_(District)": -0.005050849362155015,
      "1st_Road_Class": 0.04630093296829648,
      "1st_Road_Number": 0.003235406088237152,
      "Road_Type": 0.012504587087321007,
      "Speed_limit": -0.1264451366211499,
      "Junction_Detail": 0.04777023313147147,
      "Junction_Control": 0.05067693686741452,
      "2nd_Road_Class": 0.038737916662756174,
      "2nd_Road_Number": 0.035585069064491985,
      "Pedestrian_Crossing-Human_Control": 0.011212859909190057,
      "Pedestrian_Crossing-Physical_Facilities": -0.018420302712894104,
      "Light_Conditions": -0.054452112801539145,
      "Weather_Conditions": 0.017790798658151922,
      "Road_Surface_Conditions": -0.08314568284907624,
      "Special_Conditions_at_Site": -0.02212675733095642,
      "Carriageway_Hazards": -0.01080873874450113,
      "Urban_or_Rural_Area": -0.10267241327127857,
      "Did_Police_Officer_Attend_Scene_of_Accident": 1.0
    }
  }
}